lanelet2_parser/__init__.py
lanelet2_parser/exceptions.py
lanelet2_parser/parser.py
lanelet2_parser/lanelet2/__init__.py
lanelet2_parser/lanelet2/config.py
lanelet2_parser/lanelet2/converter.py
lanelet2_parser/lanelet2/models.py
lanelet2_parser/lanelet2/network.py
lanelet2_parser/osm/__init__.py
lanelet2_parser/osm/models.py
lanelet2_parser/osm/validator.py
lanelet2_parser-0.1.8.dist-info/METADATA
lanelet2_parser-0.1.8.dist-info/WHEEL
lanelet2_parser-0.1.8.dist-info/top_level.txt
lanelet2_parser-0.1.8.dist-info/RECORD
