Metadata-Version: 2.1
Name: lanelet2-parser
Version: 0.1.8
Summary: Parser for Lanelet2
Home-page: https://github.com/tier4/lanelet2-parser
Author: Yuki Iida
Author-email: yuki.iida@tier4.jp
License: BSD-3-Clause
Keywords: Lanelet2,Parser,Autoware
Platform: UNKNOWN
Classifier: Development Status :: 5 - Production/Stable
Classifier: License :: OSI Approved :: BSD License
Classifier: Programming Language :: Python
Classifier: Programming Language :: Python :: 3
Classifier: Programming Language :: Python :: 3.4
Classifier: Programming Language :: Python :: 3.5
Classifier: Programming Language :: Python :: 3.6
Classifier: Programming Language :: Python :: 3.7
Classifier: Topic :: Database
Classifier: Topic :: Software Development :: Libraries :: Python Modules
Requires-Dist: schematics (==2.1.0)
